deeprails/__init__.py
deeprails/_base_client.py
deeprails/_client.py
deeprails/_compat.py
deeprails/_constants.py
deeprails/_exceptions.py
deeprails/_files.py
deeprails/_models.py
deeprails/_qs.py
deeprails/_resource.py
deeprails/_response.py
deeprails/_streaming.py
deeprails/_types.py
deeprails/_version.py
deeprails/py.typed
deeprails/_utils/__init__.py
deeprails/_utils/_compat.py
deeprails/_utils/_datetime_parse.py
deeprails/_utils/_logs.py
deeprails/_utils/_proxy.py
deeprails/_utils/_reflection.py
deeprails/_utils/_resources_proxy.py
deeprails/_utils/_streams.py
deeprails/_utils/_sync.py
deeprails/_utils/_transform.py
deeprails/_utils/_typing.py
deeprails/_utils/_utils.py
deeprails/lib/.keep
deeprails/resources/__init__.py
deeprails/resources/defend.py
deeprails/resources/files.py
deeprails/resources/monitor.py
deeprails/types/__init__.py
deeprails/types/defend_create_response.py
deeprails/types/defend_create_workflow_params.py
deeprails/types/defend_response.py
deeprails/types/defend_retrieve_workflow_params.py
deeprails/types/defend_submit_and_stream_event_params.py
deeprails/types/defend_submit_and_stream_event_response.py
deeprails/types/defend_submit_event_params.py
deeprails/types/defend_update_response.py
deeprails/types/defend_update_workflow_params.py
deeprails/types/file_response.py
deeprails/types/file_upload_params.py
deeprails/types/monitor_create_params.py
deeprails/types/monitor_create_response.py
deeprails/types/monitor_detail_response.py
deeprails/types/monitor_event_detail_response.py
deeprails/types/monitor_event_response.py
deeprails/types/monitor_retrieve_params.py
deeprails/types/monitor_submit_event_params.py
deeprails/types/monitor_update_params.py
deeprails/types/monitor_update_response.py
deeprails/types/workflow_event_detail_response.py
deeprails/types/workflow_event_response.py
deeprails-1.25.0.dist-info/METADATA
deeprails-1.25.0.dist-info/WHEEL
deeprails-1.25.0.dist-info/licenses/LICENSE
deeprails-1.25.0.dist-info/RECORD
